{"2108":"pdeffebach","2261":"juliaG","7144":"rakesh_gupta","1703":"kguo","9835":"Mariana","8844":"newstatement","10100":"ahumenberger","319":"chkwon","687":"frapac","185":"joshday","13515":"ErkinK","1991":"mopg","14378":"priod","4136":"jling","3608":"sergevic","9457":"abcde","1823":"pipete40","14401":"Philip_Olhager","14689":"Antell","6595":"Xing_Shi_Cai","9370":"sudete","7991":"Miguel_Goncalves","3646":"rhuffman","2119":"artagnon","9523":"azberman","3794":"rocarvaj","6644":"gbustosx","4851":"jcreinhold","6649":"jints07","11078":"Shuhua","172":"Ralph_Smith","103":"JeffreySarnoff","6151":"levip","3549":"Lefteris_Manousakis","1171":"Wei_Wang","13038":"ZettEff","116":"Chris_Foster","279":"bdeonovic","10360":"RaulBritto","7611":"biswajit216","12860":"lrnv","6577":"Joao_Guilherme_Santo","2570":"oheil","9593":"joshuastowell25","15992":"filchristou","2783":"migarstka","1859":"jacob-roth","17249":"FH96","2336":"Rahul_Sharma","485":"s-broda","15328":"obar","3105":"BeastyBlacksmith","1861":"gcalderone","2732":"egcjm","14812":"tred","5492":"mcabbott","152":"fengyang.wang","12471":"tpmp","11261":"gustaphe","15230":"Francisco_Javier_Mar","12217":"blob","5455":"mateuszbaran","454":"bramtayl","16211":"YummyPampers2","1504":"jmatovu","6792":"Amin_Yahyaabadi","8389":"dty","13737":"user1200","5585":"Mastomaki","1095":"Pierre-Louis_Poirion","12824":"maajdl","3135":"OliverEvans96","5354":"haydenfree","2041":"Pu_He","9667":"aquarelle332","9448":"asyadav","15325":"Debasish","325":"ericsfraga","3423":"clausherther","14994":"Thomas","8442":"hdavid16","145":"cortner","558":"Thuener","342":"KrishnaKanhaiya","10279":"optimist","15184":"Piotr","1539":"UserMorocco","9960":"DKad","13254":"prit","6982":"ahmadreza-marandi","1236":"chakravala","13227":"jacobusmmsmit","8615":"contradict","3722":"Deb_Midya","1994":"Sharabh_Shukla","786":"nilshg","11899":"iHany","15474":"Popeye","92":"j_verzani","2279":"tlagos","5349":"yanyuechuixue","11023":"Ernesto_Diaz","15341":"Gabriel_Kreindler","5955":"mamuniut09","5159":"Jay_Dave","14937":"tmigot","1336":"stillyslalom","3014":"Argel_Ramirez_Reyes","18":"dpsanders","7201":"gobs","6215":"mtanneau","8801":"tdp","1612":"lkapelevich","6756":"artykbayevk","5532":"brwst","9570":"Behemoth-s","3835":"CDRPico","807":"dpo","16823":"dbomahn","899":"bbrunaud","368":"gasagna","217":"christianpeel","4153":"Phillip_Sutton","993":"Sam-H","5964":"bienpierre","61":"dave.f.kleinschmidt","7157":"Qun","3877":"timueh","10129":"uncertainly","7542":"bars","9535":"fksayaci","12184":"axw","4125":"HSFengWang","12740":"claudio20497","1238":"Duaa","6911":"Farnazmdi","13755":"maxkapur","15235":"phy-lxf","9888":"cby","11520":"trathi","678":"tamasgal","80":"dawbarton","51":"tobias.knopp","9467":"jeffreyesun","5321":"ryancorywright","490":"kkmann","9530":"ccampaigne","667":"pyrex41","508":"huckl3b3rry87","10701":"dweb","17885":"sstroemer","2978":"affans","2418":"MLackner","4663":"astor87","5725":"dmetivie","10754":"Ashwani_Rathee","7324":"pulsipher","3198":"jayce_ram","723":"carstenbauer","7423":"elalaouifaris","419":"Rory-Finnegan","6352":"Arega_Getaneh","6810":"raphaelsaavedra","5595":"kalim","3965":"juliauser","186":"kevbonham","10780":"Samuel_Ainsworth","3068":"igorteo84","2682":"moesphere","90":"slowbrain","13281":"Deepedit","3447":"Ludo","2380":"mcbaron","14783":"mengxiaoliu","3817":"jbmuir","9040":"rpetit","3196":"magister-ludi","4512":"simeonschaub","1268":"FabsOliveira","3365":"uwechsler","874":"Elrod","17769":"max","9162":"Dominic_Pazzula","3828":"opt","356":"abieler","2017":"Rudi79","7336":"jay-dave","5346":"WangQuanmeng","17816":"Joseph_Bradley","406":"RainerEngelken","643":"danspielman","702":"ccoffrin","2388":"foobar_lv2","3192":"Libbum","1642":"hhaensel","533":"mlhetland","8549":"Xentios","2019":"tobydriscoll","10":"yeesian","7682":"Codzilla","5007":"marouane","8197":"agcm","11017":"RasmusDamgaard","881":"stst","9224":"r-b0","662":"abulak","1319":"pmarg","6068":"zhangxz1123","2219":"mandart","6940":"pixel27","645":"Mattriks","6605":"eschoute","9793":"GerhardTotschnig","15182":"BYS","8226":"Caterina_Cerutti","6187":"klaff","16149":"ylish","11255":"zlq178","1588":"Kavitha","12869":"Peter_Volkmar","10513":"Shah_MF","16483":"zhangsanle","3519":"guille","884":"Harsha","6202":"DrChainsaw","123":"DNF","15089":"Djoull","2299":"Mason","11868":"dharik13","11168":"SOtani","14943":"rox","197":"oxinabox","1063":"sshrabah","7800":"varun_yaramasu","10031":"Tomas_Uribe","196":"Keno","505":"amrods","6191":"brianguenter","6461":"riccardomurri","4842":"AndiMD","12204":"awasserman","58":"viralbshah","596":"ashefa","11352":"rafael.guerra","385":"ZacLN","3566":"Toxmi","1493":"Aritra_Pal","8127":"bashonubuntu","3019":"RaquelSantos","2055":"trigaut","17317":"pboes","3056":"Stani83","17035":"s154428","8627":"Albert_Zevelev","87":"gragusa","1759":"jandehaan","7487":"Impressium","589":"cossio","2328":"yold6","7277":"NicholasWMRitchie","2273":"Rafal_Machalica","12905":"erikbjornerem","6228":"octavia9","1384":"jorgeiv500","8925":"martincornejo","9005":"DShiu","5565":"htwai","9866":"musman","12170":"SonntagK","13105":"TheMEGuy","6197":"PaulBreiding","131":"davidanthoff","5105":"mike_k","8322":"pkienscherf","6572":"RohiniShetty","53":"tim.holy","11033":"arkanver","11146":"PabloGalaz","2062":"SebastianM-C","1471":"tkluck","617":"piever","15828":"Sawyer_Zhou","2233":"Raf","181":"jrklasen","5037":"miqlliot","9353":"joergbuchwald","6699":"lesshaste","6774":"MFairley","220":"blegat","3449":"Guito","9050":"Espenol","8397":"Wedg","4804":"HerAdri","215":"lbenet","3505":"pleiby","9685":"11129","9557":"dirk","4688":"tims","5746":"PharmCat","16849":"mbah","612":"evanfields","12135":"dragond4","364":"Datseris","11371":"Runhong_Huang","7173":"giadasp","940":"fredrikekre","6569":"feanor12","1393":"HugoLhuillier","2249":"razieh95","75":"tkelman","2539":"gcabrera","3243":"LinOslo","1434":"Juan","2430":"Di11on","801":"edljk","517":"Frank_Kampas","8963":"martina","1002":"ExpandingMan","1113":"Joey_Huchette","9729":"jack_rabbit","12697":"masoug","1391":"ahassansan","7648":"thisrod","7619":"nhardy","10082":"nlaws","2411":"tlienart","13905":"Prottay_Adhikari","9744":"Cyrus_the_man","8159":"Nikos-Atzarakis","17185":"jaberdeen","15413":"yucho147","9496":"mayar","2612":"fastwave","644":"mauro","9599":"Nicolas_Slosse","9463":"Florentin_Goyens","7910":"Shor","15574":"maoc","14043":"Sylvain","1875":"CodeLenz","1544":"prescient","14912":"jbshannon","22":"johnmyleswhite","14997":"safhjkas","5776":"ncostilla","4062":"GUANCHI_LIU","5906":"Y_Li","288":"FANG_Colin","16773":"marknzed","8148":"NextMyth","14907":"sinom","3026":"gmouts","8409":"dmit","15837":"Kevin_25","400":"Tomas_Pevny","12222":"andresmorago","978":"josimar","14305":"statspy","14033":"juliamilp","309":"IlyaOrson","5113":"Balance37","3590":"ksh","2708":"Cameron_Taylor","11987":"Raj95","4048":"Summer","11086":"LBaussay","9398":"brunopjacob","2191":"fancagi","4175":"RainerHeintzmann","9276":"peterj","1793":"bhalonen","7612":"MatFi","9244":"donkeysaddle","7655":"marinarrd","7346":"newjuliauser","1352":"anodos","758":"Jedrek","3775":"Rajat_Sanyal","3499":"sbacelar","16370":"ZHEN_LIN","28":"juthohaegeman","1631":"aleksip","7659":"DR59","10762":"namch","890":"NickNack","1666":"vepiteski","84":"GunnarFarneback","6540":"joemiller","5507":"SonLe","3633":"Manny8888","3769":"borelian","1505":"gopal2017","2201":"ivo_welch","5890":"remi-garcia","13317":"LukasLundgren96","6090":"cgeoga","13622":"cheng_chen","1667":"Seif_Shebl","12195":"timquelch","11295":"paulmelis","11828":"Glaucio","9750":"sugyeong-jo","12603":"Bruno","513":"Dan","9761":"Chengda_Ji","2794":"jacobadenbaum","11650":"Micah_Mungal","17609":"Xuekui_wang","1777":"falbarelli","12496":"danuzco","1240":"charlesll","193":"greg_plowman","17867":"Bernard_narvaez","6446":"rtwalker","12964":"gaadis","2800":"braamvandyk","7280":"Oscar_Smith","14409":"aaldik","894":"adowling2","14114":"erans","9154":"olugovoy","11133":"mikkoku","1204":"loylobo","1380":"ettersi","1225":"Manish","13438":"marcobonici","7295":"Arpit_Bhatia","6556":"pistacliffcho","4970":"rmilark","2731":"erikfilias","9726":"ramon.abritta","9173":"TheLateKronos","6330":"yan25y","4806":"FujiwaraTakumiEH","6318":"WILSON_MASIH","8374":"mahsap58","1231":"Ayse_Nur_Arslan","253":"daschw","16267":"iagoschavarry","2193":"Wikunia","9680":"Frederic_Gilt","11014":"vaglino","4428":"Ajaychat3","10609":"m.lavaiyan","7548":"andrewrosemberg","10663":"geoffroyleconte","4360":"Giovanna_Abreu","13190":"cyanzhao42","17408":"Dan_Micsa","15448":"ciba12","12457":"asa","6134":"merlin","7446":"ToucheSir","10801":"Fathya.Salih","12060":"Elmo","11488":"davide-f","1485":"mohamed82008","852":"Yankai_Cao","5713":"CameronBieganek","13358":"Michael_Barmann","382":"Tero_Frondelius","12429":"BuRanran","654":"lostella","14080":"mirungu","3301":"coroa","675":"Skoffer","5792":"mleprovost","5287":"Luigi_Marongiu","312":"ufechner7","11396":"srajan76","13588":"fredih","81":"mauro3","2127":"Kenney","6144":"roi.holtzman","1078":"tomerarnon","1490":"ivborissov","6513":"Ross_Boylan","13351":"patrick-kidger","4709":"Marc.Cox","9":"kristoffer.carlsson","7224":"TheLoooser","3736":"Jacob_Stevens-Haas","409":"anon43133060","4554":"Reza","16654":"etas","88":"Tamas_Papp","5458":"chelseas","4788":"Paul_Schrimpf","2287":"Marcom","260":"xiaoweiz","971":"FransdR","2910":"TPDS1993","12667":"teriiju","984":"ElOceanografo","6818":"eltuck","10990":"bdc","12936":"yips","4964":"ericphanson","9702":"danicaratelli","4110":"sysk_msk","636":"holger","16006":"dbennett1994","7674":"rio","10510":"akahs","1353":"jekbradbury","496":"marius311","15430":"thompsonmj","10381":"rajnrao","14942":"shce","3456":"CPPhysics","11531":"samerb","13132":"jshengdb","2342":"Juser","12067":"Qinyang","635":"Nosferican","7959":"Julius_Martensen","1389":"iaravena","5933":"haokuny","4039":"apo383","1445":"jpsamaroo","5866":"torgo","11789":"sogrbilja","3401":"sarnatas","1112":"andrewg","9839":"chris-b1","9980":"MJMB","1084":"anriseth","1133":"Crghilardi","9983":"roflmaostc","434":"tomaklutfu","2244":"iwelch","7480":"orialb","7894":"Tamuzd","7949":"jonniedie","5061":"fusion809","277":"jesse","854":"miguelraz","4518":"zdenek_hurak","377":"joaquimg","14641":"ocolluphid","9624":"aliceee","8417":"Nikos_Gianniotis","4006":"ArjunNarayanan","7779":"logankilpatrick","1316":"ajkeith","1206":"Jonathan_Droxler","2338":"platawiec","3531":"pull_over93","11677":"Emmanouil_Bakirtzis","13128":"PaoloBova","1799":"MCSikivie","106":"crbinz","12932":"kat_mt","6956":"Alxg","102":"waldyrious","15018":"jairorua","21":"mbauman","14843":"jcert","440":"Ronis_BR","1577":"axsk","10137":"Ian_Slagle","8847":"aaronpeikert","5999":"ferrolho","5558":"willu47","9993":"ZdM87","14337":"felcbd","9516":"Smith","10930":"JLDC","2875":"mbesancon","2404":"s_bhattacharjee","3842":"GabrielYin","1950":"saschatimme","12898":"kausban","13481":"adropintheriver","7818":"Ariel_Cruz_Cruz","11939":"htpusa","6693":"dlakelan","306":"jkbest2","12051":"BenjaminBastidas","13240":"Jae-Mo_Lihm","14572":"RaulRib","14957":"AndresCasillas","16391":"Hirnfolter","4864":"PastelBelem8","12858":"Peter-Jolly","6277":"pedrohvbsilva","3424":"zekeriya.sari","1010":"anon94023334","4316":"dmolina","11781":"MarcMush","5264":"danielcas","115":"mkborregaard","3371":"tfk17lstm","16088":"alfajar_nugraha","13569":"boranzhao","1468":"PetrKryslUCSD","12071":"cricci","7502":"juandarias","584":"rveltz","16131":"Mario_mushroom","1844":"SingingKim","2643":"Gaussia","2057":"yha","3484":"jdeboeck","23":"joehuchette","41":"stevengj","3777":"jtackm","1702":"gbaesso","9772":"bielim","2154":"Gregstrq","16165":"Daniel_Villamar","17184":"John_Peach","8663":"RangeFu","15329":"Dan.phi","336":"floswald","755":"lstagner","11254":"Gaiato","12747":"Huy_Nguyen","7163":"jd-foster","4425":"DrPapa","14949":"arfuentes97","247":"tkoolen","11799":"JLHTM","8597":"rikh","10981":"GeneralPoxter","9738":"linde-fr","3251":"jdlara-berkeley","11957":"vattyamv","8687":"Hector_Esteban","2218":"jaakkor2","9573":"Markus_Hauschel","1257":"Frank_Kampas1","2782":"nhipsman","15296":"Armando_Gabriel_Guar","6733":"lgo","13447":"tholdem","1885":"jzakiya","8818":"Maximilian","10282":"scotts","8063":"Val","7373":"Natedogg373","1924":"crinders","11325":"hassanis","6388":"pandeysudan27","5":"sdanisch","8474":"jadosfer","1599":"Amulya_Yadav","10816":"barguzin","9740":"Henderson","747":"Donald_Lacombe","14612":"Yasmine_123","11145":"jguo","7104":"MuadhF","13666":"thorek1","954":"traktofon","13156":"Flesko","530":"pearlzli","8987":"mkitti","3069":"AnttiSim","437":"robertfeldt","5505":"neseth","7903":"infinitylabs","2125":"jcook","148":"jw3126","10940":"Liang_Chen","2505":"andreas-ernst","791":"deepakagrawal","2264":"brynpickering","17268":"krusharth.shah","11661":"martinbiel","7":"avik","13929":"egvila","8588":"zxjroger","7074":"alequa","1747":"acauligi","5740":"Johncowk","17330":"Brock","3992":"OvidiusCicero","10857":"stephentu","16226":"bgladman","11383":"umbe","583":"jgreener64","44":"miles.lubin","13014":"bvilmann","2429":"Joris_Pinkse","13107":"sui","12631":"yewalenikhil65","8853":"jagot","1089":"philipithomas","576":"odow","6593":"freemint","5644":"Roshan.Sharma","9042":"cupcc","9234":"SteffenPL","4162":"cdawg","11877":"mrt","4519":"chisquared","7828":"4aHxKzD","4520":"aplavin","4683":"nrontsis","9169":"Ken_Lin","246":"chriscoey","1263":"NiclasMattsson","3908":"Sukera","4595":"korpuskel","8160":"jovansam","4874":"amca01","648":"monty","13468":"NickRedwood","14780":"priantop","1248":"healyp","614":"leclere","5395":"mthelm85","9399":"Newton-Climate","11991":"valenmgama","1215":"askvorts","3959":"thautwarm","9654":"metab0t","359":"abhijeetpanda12","1516":"Dandan","3036":"Somayeh_Esmaeili","5244":"ndinsmore","7492":"PyDataBlog","6140":"ibabeo","3666":"muriloasouza","2424":"g001234","2596":"cfrodriguez","1857":"Neurovium","10755":"Luca","6729":"Fisheryu1234","3017":"yoeljacobsen","9311":"brett_knoss","17534":"XLVII","11":"simonbyrne","10322":"Pritesh_Shrivastava","2384":"dourouc05","838":"Tal_Raviv","15790":"til1","13167":"xyz1","12568":"f6v","2196":"leaoshark","11186":"fnbillimoria","8383":"rdoelman","6936":"PatrickHealy","2387":"Luiz","14711":"Paris_Pijuan","5594":"Utkarsh_Konge","1785":"bstellato","17431":"Lwshalls","257":"rdeits","200":"Stephen_Vavasis","4465":"Rasoul","213":"pkofod","647":"Palli","8206":"baprata","15197":"iiitr","9899":"NightMachinary","10907":"raphaelchinchilla","16761":"bsturt","5074":"xor0110","3596":"axelle","12853":"Amirrezz94","445":"jlapeyre","6274":"iharjunk","1791":"dilumaluthge","10689":"sobhan","7448":"lausilvag","10917":"LHR","6526":"deschase","3766":"dapz","3389":"lwhitefox","5387":"guilhermebodin","917":"spuschel","16736":"vinicius_de_lima","859":"Jason","13158":"mreguant","24":"nalimilan","6685":"Hakan_Kjellerstrand","10382":"lungd","5771":"HenriDeh","13026":"Jaidy","1421":"mrapo","7569":"Saggaa","1552":"oschulz","433":"sylvaticus","1005":"Pigskinablanket","4530":"Zhiye_Xia","12436":"b2jia","1165":"Angshuman_Goswami","6721":"Raminel","933":"RoyiAvital","15985":"adityac","3246":"LaurentPlagne","913":"felipenoris","7415":"ys3636","2544":"Alvaro_Jose_Gonzalez","7160":"casv2","268":"colintbowers","1647":"Jon_Norberg","792":"gdowdy3","8954":"indycdrom","6208":"mzhenirovskyy","4350":"cosmia","5480":"hzgzh","5692":"murphyk","4573":"fa-bien","17061":"Lessvn","10459":"josePereiro","16903":"goerch","1540":"Joao_Saran","14191":"hustkisas","13879":"kwokhao","10492":"Akatz","13512":"cm0","11259":"mamo","1671":"mschauer","15849":"twelvespot","5867":"rev","8471":"cvanaret","5136":"Olegg","13199":"vjimenezg","9646":"python15","5547":"Arno","9371":"SAH","4744":"orhan_abar","1851":"xiaodai","12361":"malacroi","15020":"marcus-waldman","9077":"shiroghost","9297":"ykc","15735":"Jameli","180":"mzaffalon","7528":"liuyxpp","8324":"StarecZosima","6879":"ohmsweetohm1","6207":"bocc","4696":"tobi","17428":"duringyear","9078":"cmarcotte","4493":"mpal","9071":"bandaya","17751":"mottelet","670":"ko56","6801":"rcallen24","332":"aaowens","7081":"fliteplan","229":"Paul_Soderlind","7009":"scottstanie","13826":"ForceBru","11806":"cotepascal76","3866":"Lucas_Pollito","5170":"YoungFaithful","2589":"non-Jedi","3":"sglyon","1984":"tbeason","96":"gabrielgellner","7213":"anubhavratha","2280":"Qifeng","504":"jwu","2095":"Paul_McVay","3583":"Vondoe79","11118":"1ozturkbe","4351":"Ryao","1247":"JackDevine","4138":"stelmo","1855":"XavierG","2096":"alejandromerchan","10088":"noamgold","2780":"shoshievass","1188":"Shimrit_Shtern","2236":"grahamas","2333":"Shuvomoy_Das_Gupta","9612":"RibeiroRaul","5674":"anon92994695","1692":"jlperla","417":"iamed2","333":"juliohm","8592":"DanielPompermayer","1742":"Bernard_GODARD","5561":"longemen3000","9633":"Humphrey_Lee","603":"Nitin_Arora","13821":"GraceMabele","376":"jtravs","4416":"skam","1569":"KestutisMa","12":"yuyichao","8779":"L_Adam","13757":"Kreiton_Sitorus","12210":"rezabayani","5914":"ErwanPiR","17066":"Yunus_Kovankaya","17059":"graidl","1632":"Vaibhavdixit02","1280":"davidzentlermunro","9778":"jakub1998","26":"ararslan","571":"mposs","12218":"julianoob","7054":"Jakub_Wronowski","16574":"geo","15357":"eipi10","7735":"compleat","4935":"coiacy","15617":"Hilaire_Foillard","15928":"Annette_F","11050":"tonygem96","9607":"richard046","14656":"mjanun","4341":"Seanny123","8225":"markusb","956":"Bart_Jenkins","994":"leejm516","129":"PeterSimon","7067":"hendri54","878":"varun7rs","14518":"Yaropro14","313":"abelsiqueira","8671":"waumpel","11486":"Tmart","588":"hellemo","9543":"GavinRay","2363":"MaximilianJHuber","2822":"rdbrackston","3254":"Zacharie_ALES","6770":"Octarosu","432":"johnh","4500":"ssriram1992","9771":"JohnZ","8525":"jonmat","3673":"mkt","12315":"Batuhan_Guvenc","7326":"Dota","5484":"Sebastian_Rollen","3102":"vtjeng","3889":"itzui","624":"phlavenk","2272":"alusiani","10627":"renke.kuhlmann","855":"gavelasq","6075":"angeloaliano1","8893":"lungben","15052":"yecyn","14764":"etienne_dg","17746":"Gleb_Belov","10642":"mvsoom","17291":"qiujj","11212":"afazevedo","2753":"andrewning","9862":"PearsonCHEN","3619":"mm0063","9250":"nboyd","3891":"bennedich","2549":"pjssilva","11458":"Dyranne","8256":"JosiahPohl","553":"yakir12","751":"PLP","5437":"AtsushiSakai","9379":"viralnatani","2005":"Halil1","5474":"asavasci","6066":"Andre_Mello","2365":"airpmb","11216":"votroto","14312":"acwkim","3302":"pierre-haessig","16":"ihnorton","8863":"mingjia1025","2276":"CanLi1","3612":"Zranz","712":"smldis","12638":"shashankchahar","489":"mcreel","1536":"Julie","12146":"jzr","14745":"manoj.centura","16186":"aiiiob_bie","580":"Azzaare","16113":"oli1119","12840":"faisal_moh","6443":"dburch","6045":"amontoison","1880":"vgdev","421":"joshualeond","4028":"eliassno","16519":"SupplyChef","12789":"carlos","1573":"Ksun46","585":"antoine-levitt","10745":"sunjin","4394":"josemaria","16580":"Aida_Khajavirad","11037":"beske","5559":"Mahbubar06","7919":"squirrel","15":"StefanKarpinski","11204":"adow031","2315":"Andrey_Stroil","8854":"GiuliaM","7628":"jlchan","2837":"tkf","1100":"xqrongm","219":"mbeltagy","7911":"Leonardo_Rivera","3388":"briochemc","3849":"CBongiova","10723":"nluetts","3497":"jdad","13":"jrevels","2922":"mpf01","16619":"danphenderson","1444":"anon61610682","6109":"nitu0317","3349":"Igor_Douven","6188":"ilias","4684":"Prashant_Chintapalli","3430":"Isabela_Valonni","850":"Per","9265":"dcutler","2018":"misha_mikhasenko","539":"leethargo","9314":"Lukros","17871":"kchnkrml","13721":"gustav.asbjorn","441":"rcnlee","955":"Vincent_Zoonekynd","4170":"yordiak","4733":"damaro","15064":"phantom","3529":"scheidan","13080":"Maria95","7948":"Josa9321","5612":"bnarum","16445":"jeanluc","7268":"Diego","481":"pedroborgesmelo","161":"giordano","11129":"zazizoma","6938":"owiecc","3503":"drarnau","3586":"FMeirinhos","9927":"claytonpbarrows","6421":"Vasily_Pisarev","545":"John_Gibson","1658":"michaellindon","17240":"wangpuming","8":"MikeInnes","14365":"arseny-sandaar","7561":"raktim","83":"pfitzseb","201":"glemieux","99":"ChrisRackauckas","554":"mforets","11675":"Wesley_Coelho","386":"JaredCrean2","491":"ggggggggg","9703":"nicolas","11108":"aross","1509":"rayset","1456":"haberdashPI","3005":"EgidioLeo","10868":"gedankenexperiment","1572":"y4lu","10676":"Janssena","8466":"reumle","7587":"cpross90","8031":"seba754","7783":"dadada_dadada","13037":"Soumya_Boral","5104":"rotsoc","4664":"jwveysey","17062":"joe_sonic","3776":"ImreSamu","7073":"faoh","14765":"hxxx123","5348":"jmcastro2109","2522":"Anton_Hinneck","16377":"oscarknagg","11451":"path-doc","1410":"depasquale","7170":"wenqi_kou","5920":"XVilka","14504":"shanmukhan","256":"grandemundo82","188":"nantonel","16732":"Nenndul","12030":"standon41","2759":"ianfiske","16774":"giulia","4931":"skarp","17564":"Matheus_Diogenes_And","11841":"avonmoll","10225":"Bogo","880":"bjenkinsgit","371":"jonathanBieler","16245":"Strange_Xue","76":"Oliver_Lylloff","2697":"Curious1","4146":"leandromartinez98","11265":"Luis_Tormo","2286":"BLI","9551":"gleyland","7666":"kuwi","6553":"Yuya-Furusawa","2006":"Gunter_Faes","1430":"loisel","3287":"Azamat","3500":"rawls238","1888":"J_T","3816":"Stuart_Rogers","5277":"Hamoum_Belaid","1032":"baggepinnen","128":"TsurHerman","9462":"marcus","350":"omalled","3592":"HCrepaz","38":"tshort","12156":"bicepjai","326":"samuelpowell","939":"MarioSouto","7986":"ctkelley","16339":"ver_kh","10547":"viraltux","944":"Arrigo_Benedetti","10437":"anon37204545","6909":"alvrg","17264":"Ali9266","9218":"edwinb-ai","611":"copti","5441":"krenova","12196":"nico","6664":"Henrique_Becker","1608":"IssamT","14795":"runjaj","887":"tyleransom","8003":"kuro26"}